{
    "title": "Executable Tutorial",
    "description": "DevSecOps with Checkov for Infrastructure Security Scanning",
    "details": {
        "intro": {
            "text": "intro.md",
            "background": "background.sh"
        },
        "steps": [
            {
                "text": "step1/step1.md"
            },
            {
                "text": "step2/step2.md",
                "background": "step2/background.sh",
                "foreground": "step2/foreground.sh"
            },
            {
                "text": "step3/step3.md"
            },
            {
                "text": "step4/step4.md"
            },
            {
                "text": "step5/step5.md"
            }
        ],
        "finish": {
            "text": "finish.md"
        }
    },
    "backend": {
        "imageid": "ubuntu"
    },
    "interface": {
        "layout": "ide"
    }
}